pass_generator/__init__.py
pass_generator/generator.py
holosen_pass_generator-0.1.1.dist-info/METADATA
holosen_pass_generator-0.1.1.dist-info/WHEEL
holosen_pass_generator-0.1.1.dist-info/top_level.txt
holosen_pass_generator-0.1.1.dist-info/RECORD
