Metadata-Version: 2.1
Name: holosen-pass-generator
Version: 0.1.1
Summary: A simple Python library to generate 3 type of password
Home-page: https://github.com/holosenpythonknight/password-generator
Author: Python Knight
Author-email: holosenpythonknight@gmail.com
Classifier: Programming Language :: Python :: 3
Classifier: License :: OSI Approved :: MIT License
Classifier: Operating System :: OS Independent
Requires-Python: >=3.6
